tubex2/__init__.py
tubex2/__main__.py
tubex2/exceptions.py
tubex2/extract.py
tubex2/query.py
tubex2/stream.py
tubex2/version.py
tubex2-1.0.2.dist-info/METADATA
tubex2-1.0.2.dist-info/WHEEL
tubex2-1.0.2.dist-info/licenses/LICENSE
tubex2-1.0.2.dist-info/RECORD
