Metadata-Version: 2.1
Name: tubex2
Version: 1.0.2
Summary: Quick and easy-to-use package that allows downloading videos from YouTube both synchronously and asynchronously
Project-URL: Homepage, https://github.com/Alsond5/tubex2
Author: Alson5
License-Expression: Unlicense
License-File: LICENSE
Keywords: async,download,youtube
Classifier: License :: OSI Approved :: The Unlicense (Unlicense)
Classifier: Operating System :: OS Independent
Classifier: Programming Language :: Python :: 3
Requires-Python: >=3.10
Requires-Dist: httpx[http2]
